{
    "title": "Ciudades de papel",
    "uuid": "f0176a97-cd88-4a7a-9d8c-8e6e8e89be15",
    "subject": [
        "Novela",
        "Juvenil"
    ],
    "readers": 0,
    "added": "1674320051",
    "creator": "John Green",
    "description": "Una joven desparece dejando una serie de pistas que sólo su mejor amigo de la infancia podrá descifrar… En su último año de instituto, Quentin no ha aprobado ni en popularidad ni en asuntos del corazón… Pero todo cambia cuando su vecina, la legendaria, inalcanzable y enigmática Margo Roth Spiegelman, se presenta en mitad de la noche para proponerle que le acompañe en un plan de venganza inaudito. Después de una intensa noche que reaviva el vínculo de una infancia compartida y parece sellar un nuevo destino para ambos, Margo desaparece dejando tras de sí un extraño cerco de pistas.",
    "flow": [],
    "likes": 0,
    "comments": 0,
    "cover": "Images\/cover.jpg",
    "chapters": []
}